{
  "version": "1.0.0",
  "description": "轻灵 Qling — local-first Chinese AI Agent CLI workbench",
  "homepage": "https://github.com/Zzy-min/qling",
  "license": "MIT",
  "notes": [
    "DRAFT manifest — not published to an official Scoop bucket.",
    "Requires Node.js >= 18 on PATH.",
    "Replace url/hash with a pinned npm tarball or GitHub Release asset before publishing.",
    "API keys must be set as user environment variables (never commit secrets)."
  ],
  "depends": [
    "nodejs"
  ],
  "url": "https://registry.npmjs.org/@qlingzzy/qling/-/qling-1.0.0.tgz",
  "hash": "TODO_REPLACE_WITH_SHA256_OF_TGZ",
  "extract_dir": "package",
  "bin": "bin\\qling.cmd",
  "post_install": [
    "Write-Host 'If bin shim is missing, run: npm install -g @qlingzzy/qling@$version' -ForegroundColor Yellow",
    "Write-Host 'Then: qling bootstrap && qling setup' -ForegroundColor Cyan"
  ],
  "checkver": {
    "github": "https://github.com/Zzy-min/qling"
  },
  "autoupdate": {
    "url": "https://registry.npmjs.org/@qlingzzy/qling/-/qling-$version.tgz"
  }
}
